{"enemy_mushroom":{"height_value":32,"__target_class":["SuperMarioBros","BattleEnemyMushroom"],"width_value":28,"__childs":[{"col_count":2,"__class":"Sprite","height_value":32,"x_value":2,"width_value":32,"__link":"_sprite","texture_name":"enemy_1.png"}],"__class":"DisplayLayout"},"title_item":{"height_value":60,"__class":"DisplayLayout","width_value":22,"width_type":4,"__childs":[{"text":"MATIO","__class":"Text","x_value":42,"y_value":3,"font_path":"ClearSans-Bold.ttf","font_size":20},{"text":"0000000","__class":"Text","__link":"_score","x_value":42,"y_value":29.25,"font_path":"ClearSans-Bold.ttf","font_size":20},{"text":"00","__class":"Text","__link":"_coin","x_value":188,"y_value":29.25,"font_path":"ClearSans-Bold.ttf","font_size":20},{"text":"x","__class":"Text","x_value":171,"y_value":27.25,"font_path":"ClearSans-Bold.ttf","font_size":20},{"__extends":"small_coin_1","y_value":36.25,"x_value":153,"__module":"SuperMarioBros"},{"text":"WORLD","__class":"Text","x_value":324,"y_value":3,"font_path":"ClearSans-Bold.ttf","font_size":20},{"text":"1-1","__class":"Text","__link":"_stage","x_value":339,"y_value":32,"font_path":"ClearSans-Bold.ttf","font_size":20},{"text":"TIME","__class":"Text","x_value":440,"y_value":3,"font_path":"ClearSans-Bold.ttf","font_size":20},{"text":"000","__class":"Text","__link":"_time","x_value":440,"y_value":32,"font_path":"ClearSans-Bold.ttf","font_size":20}]},"random_wall_1":{"col_count":3,"texture_name":"random_wall.png","interval":240,"width_value":32,"__class":"SpritePlay","height_value":32},"effect_coin_text":{"font_path":"ClearSans-Bold.ttf","text":"123456789","__class":"Text","font_size":15},"player_1":{"height_value":64,"__target_class":["SuperMarioBros","BattlePlayer"],"width_value":32,"__childs":[{"col_count":7,"row_count":2,"texture_name":"player1_level_1_right.png","height_value":32,"width_value":32,"__link":"_level_1_sprite_right","__class":"Sprite"},{"col_count":7,"row_count":2,"texture_name":"player1_level_1_left.png","height_value":32,"width_value":32,"__link":"_level_1_sprite_left","__class":"Sprite"},{"col_count":7,"row_count":2,"__class":"Sprite","height_value":64,"width_value":32,"__link":"_level_2_sprite_right","texture_name":"player1_level_2_right.png"},{"col_count":7,"row_count":2,"__class":"Sprite","height_value":64,"width_value":32,"__link":"_level_2_sprite_left","texture_name":"player1_level_2_left.png"},{"col_count":7,"row_count":2,"__class":"Sprite","height_value":64,"width_value":32,"__link":"_level_3_sprite_right","texture_name":"player1_level_3_right.png"},{"col_count":7,"row_count":2,"__class":"Sprite","height_value":64,"width_value":32,"__link":"_level_3_sprite_left","texture_name":"player1_level_3_left.png"}],"__class":"DisplayLayout"},"enemy_1":{"col_count":2,"texture_name":"enemy_1.png","interval":240,"width_value":32,"__class":"SpritePlay","height_value":32},"effect_coin":{"col_count":3,"__class":"SpritePlay","interval":60,"width_value":12,"texture_name":"big_coin_1.png","height_value":28},"scroll_screen":{"container":{"__extends":"scroll_container","__module":"SuperMarioBros"},"__class":"ScrollScreen","height_type":4,"bottom_scrollbar":{"__extends":"scroll_bar","__module":"SuperMarioBros"},"width_type":4},"wall_split_anti":{"loop_map":{"split":{"childs":[{"attribute":"x","childs":[{"clazz":"LoopLinear","delay_time":0,"target":120,"total_time":1000}],"link":"_right_up"},{"attribute":"y","childs":[{"clazz":"LoopRit","delay_time":0,"target":-64,"total_time":400},{"clazz":"LoopRit","delay_time":0,"target":300,"total_time":600}],"link":"_right_up"},{"attribute":"x","childs":[{"clazz":"LoopLinear","delay_time":0,"target":120,"total_time":1000}],"link":"_right_bottom"},{"attribute":"y","childs":[{"clazz":"LoopRit","delay_time":0,"target":0,"total_time":400},{"clazz":"LoopRit","delay_time":0,"target":268,"total_time":600}],"link":"_right_bottom"},{"attribute":"angle","childs":[{"clazz":"LoopLinear","delay_time":0,"target":90,"total_time":1000}],"link":"_right_up"},{"attribute":"angle","childs":[{"clazz":"LoopLinear","delay_time":0,"target":90,"total_time":1000}],"link":"_right_bottom"},{"attribute":"x","childs":[{"clazz":"LoopLinear","delay_time":0,"target":-120,"total_time":1000}],"link":"_left_up"},{"attribute":"y","childs":[{"clazz":"LoopRit","delay_time":0,"target":-64,"total_time":400},{"clazz":"LoopRit","delay_time":0,"target":300,"total_time":600}],"link":"_left_up"},{"attribute":"angle","childs":[{"clazz":"LoopLinear","delay_time":0,"target":-90,"total_time":1000}],"link":"_left_up"},{"attribute":"x","childs":[{"clazz":"LoopLinear","delay_time":0,"target":-120,"total_time":1000}],"link":"_left_bottom"},{"attribute":"y","childs":[{"clazz":"LoopRit","delay_time":0,"target":0,"total_time":400},{"clazz":"LoopRit","delay_time":0,"target":268,"total_time":600}],"link":"_left_bottom"},{"attribute":"angle","childs":[{"clazz":"LoopLinear","delay_time":0,"target":-90,"total_time":1000}],"link":"_left_bottom"}]}},"height_value":32,"width_value":32,"__childs":[{"row_count":22,"col_count":26,"__class":"Sprite","texture_name":"tile_map.png","height_value":16,"width_value":16,"__link":"_left_up","col_index":11},{"col_count":26,"__class":"Sprite","x_value":16,"col_index":12,"texture_name":"tile_map.png","height_value":16,"width_value":16,"__link":"_right_up","row_count":22},{"col_count":26,"row_count":22,"y_value":16,"col_index":11,"texture_name":"tile_map.png","__class":"Sprite","height_value":16,"width_value":16,"__link":"_left_bottom","row_index":2},{"col_count":26,"row_count":22,"x_value":16,"y_value":16,"col_index":12,"texture_name":"tile_map.png","__class":"Sprite","height_value":16,"width_value":16,"__link":"_right_bottom","row_index":2}],"__class":"DisplayLayout"},"scroll_bar_btn":{"show_up":{"__class":"Grid9Image","left_size":5,"width_type":1,"bottom_size":10,"texture_name":"btn_up.png","height_type":1,"right_size":9,"width_value":30,"height_value":28,"top_size":5},"show_down":{"__class":"Grid9Image","left_size":5,"width_type":1,"bottom_size":10,"texture_name":"btn_down.png","height_type":1,"right_size":9,"width_value":30,"height_value":28,"top_size":5},"show_disabled":{"__class":"Grid9Image","left_size":5,"width_type":1,"bottom_size":10,"texture_name":"btn_down.png","height_type":1,"right_size":9,"width_value":30,"height_value":28,"top_size":5},"__class":"TextButton","width_value":30,"height_value":28,"show_over":{"__class":"Grid9Image","left_size":5,"width_type":1,"bottom_size":10,"texture_name":"btn_up.png","height_type":1,"right_size":9,"width_value":30,"height_value":28,"top_size":5}},"wall_1":{"col_count":13,"height_value":32,"row_count":11,"texture_name":"tile_map.png","width_value":32,"__class":"Sprite","col_index":6},"life_mushroom":{"height_value":32,"__target_class":["SuperMarioBros","BattleLifeMushroom"],"width_value":32,"texture_name":"lifemushroom.png","__class":"Image"},"flag_4":{"row_index":4,"col_count":13,"height_value":32,"texture_name":"tile_map.png","__class":"Sprite","width_value":32,"row_count":11,"col_index":3},"stage_scene":{"height_value":460,"__target_class":["SuperMarioBros","StageScene"],"__childs":[{"green":0,"__class":"Quad","height_type":4,"red":0,"width_type":4,"blue":0},{"__extends":"title_item","__module":"SuperMarioBros"},{"y_type":3,"text":"WORLD","__class":"Text","font_path":"ClearSans-Bold.ttf","x_value":-73.5,"y_value":-64,"x_type":3,"font_size":25},{"__class":"Text","x_value":46,"y_value":-64,"font_path":"ClearSans-Bold.ttf","text":"1-1","y_type":3,"x_type":3,"__link":"_stage_text","font_size":25},{"__class":"Text","x_value":31,"y_value":4.6666666666667,"font_path":"ClearSans-Bold.ttf","text":"3","y_type":3,"x_type":3,"__link":"_life_text","font_size":25},{"font_path":"ClearSans-Bold.ttf","text":"x","__class":"Text","y_type":3,"x_value":-13,"y_value":4.6666666666667,"x_type":3,"font_size":25},{"texture_name":"player_icon.png","y_value":4.6666666666667,"height_value":32,"__class":"Image","x_value":-63,"width_value":32,"x_type":3,"y_type":3}],"__class":"DisplayLayout","width_value":560},"flag_5":{"row_index":8,"col_count":13,"height_value":32,"row_count":11,"__class":"Sprite","width_value":32,"texture_name":"tile_map.png","col_index":12},"big_coin_1":{"col_count":3,"texture_name":"big_coin_1.png","interval":240,"width_value":24,"__class":"SpritePlay","height_value":28},"flag_2":{"row_index":4,"col_count":13,"height_value":32,"texture_name":"tile_map.png","__class":"Sprite","width_value":32,"row_count":11,"col_index":4},"hide_wall_1":{"col_count":13,"texture_name":"tile_map.png","height_value":32,"row_count":11,"width_value":32,"__class":"Sprite","col_index":7},"enemy_2":{"col_count":2,"texture_name":"enemy_2.png","interval":240,"width_value":32,"height_value":48,"__class":"SpritePlay"},"scroll_bar":{"down_button":{"__extends":"scroll_bar_btn"},"total_size":100,"bar_button":{"__extends":"scroll_bar_btn"},"down_size":20,"type":1,"up_button":{"__extends":"scroll_bar_btn"},"show_size":20,"height_value":20,"width_value":200,"up_size":20,"__class":"ScrollBar"},"small_coin_1":{"col_count":3,"texture_name":"small_coin_1.png","interval":240,"width_value":14,"height_value":16,"__class":"SpritePlay"},"born_1":{"col_count":7,"texture_name":"player1_level_1_right.png","row_count":2,"width_value":32,"__class":"Sprite","height_value":32},"flag_3":{"row_index":5,"col_count":13,"height_value":32,"row_count":11,"__class":"Sprite","width_value":32,"texture_name":"tile_map.png","col_index":4},"scroll_container":{"width_type":4,"__target_class":["SuperMarioBros","EditContainer"],"__class":"DisplayLayout","height_type":4},"login_scene":{"__class":"DisplayLayout","__target_class":["SuperMarioBros","LoginScene"],"__childs":[{"green":0.58039215686275,"__class":"Quad","height_type":4,"red":0.36078431372549,"width_type":4,"blue":0.98823529411765},{"__class":"DisplayView","__childs":[{"height_value":32,"__childs":[{"col_count":13,"texture_name":"tile_map.png","row_count":11,"width_value":32,"__class":"Sprite","height_value":32},{"col_count":13,"row_count":11,"texture_name":"tile_map.png","width_value":32,"__class":"Sprite","height_value":32},{"col_count":13,"row_count":11,"texture_name":"tile_map.png","width_value":32,"__class":"Sprite","height_value":32},{"col_count":13,"row_count":11,"texture_name":"tile_map.png","width_value":32,"__class":"Sprite","height_value":32},{"col_count":13,"row_count":11,"texture_name":"tile_map.png","width_value":32,"__class":"Sprite","height_value":32},{"col_count":13,"row_count":11,"texture_name":"tile_map.png","width_value":32,"__class":"Sprite","height_value":32},{"col_count":13,"row_count":11,"texture_name":"tile_map.png","width_value":32,"__class":"Sprite","height_value":32},{"col_count":13,"row_count":11,"texture_name":"tile_map.png","width_value":32,"__class":"Sprite","height_value":32},{"col_count":13,"row_count":11,"texture_name":"tile_map.png","width_value":32,"__class":"Sprite","height_value":32},{"col_count":13,"row_count":11,"texture_name":"tile_map.png","width_value":32,"__class":"Sprite","height_value":32},{"col_count":13,"row_count":11,"texture_name":"tile_map.png","width_value":32,"__class":"Sprite","height_value":32},{"col_count":13,"row_count":11,"texture_name":"tile_map.png","width_value":32,"__class":"Sprite","height_value":32},{"col_count":13,"row_count":11,"texture_name":"tile_map.png","width_value":32,"__class":"Sprite","height_value":32},{"col_count":13,"row_count":11,"texture_name":"tile_map.png","width_value":32,"__class":"Sprite","height_value":32},{"col_count":13,"row_count":11,"texture_name":"tile_map.png","width_value":32,"__class":"Sprite","height_value":32},{"col_count":13,"row_count":11,"texture_name":"tile_map.png","width_value":32,"__class":"Sprite","height_value":32},{"col_count":13,"row_count":11,"texture_name":"tile_map.png","width_value":32,"__class":"Sprite","height_value":32},{"col_count":13,"row_count":11,"texture_name":"tile_map.png","width_value":32,"__class":"Sprite","height_value":32}],"__class":"Linear","y_value":19,"width_type":4,"y_type":4},{"__class":"Linear","__childs":[{"col_count":13,"row_count":11,"texture_name":"tile_map.png","width_value":32,"__class":"Sprite","height_value":32},{"col_count":13,"texture_name":"tile_map.png","row_count":11,"width_value":32,"__class":"Sprite","height_value":32},{"col_count":13,"texture_name":"tile_map.png","row_count":11,"width_value":32,"__class":"Sprite","height_value":32},{"col_count":13,"texture_name":"tile_map.png","row_count":11,"width_value":32,"__class":"Sprite","height_value":32},{"col_count":13,"texture_name":"tile_map.png","row_count":11,"width_value":32,"__class":"Sprite","height_value":32},{"col_count":13,"texture_name":"tile_map.png","row_count":11,"width_value":32,"__class":"Sprite","height_value":32},{"col_count":13,"texture_name":"tile_map.png","row_count":11,"width_value":32,"__class":"Sprite","height_value":32},{"col_count":13,"texture_name":"tile_map.png","row_count":11,"width_value":32,"__class":"Sprite","height_value":32},{"col_count":13,"texture_name":"tile_map.png","row_count":11,"width_value":32,"__class":"Sprite","height_value":32},{"col_count":13,"texture_name":"tile_map.png","row_count":11,"width_value":32,"__class":"Sprite","height_value":32},{"col_count":13,"texture_name":"tile_map.png","row_count":11,"width_value":32,"__class":"Sprite","height_value":32},{"col_count":13,"texture_name":"tile_map.png","row_count":11,"width_value":32,"__class":"Sprite","height_value":32},{"col_count":13,"texture_name":"tile_map.png","row_count":11,"width_value":32,"__class":"Sprite","height_value":32},{"col_count":13,"texture_name":"tile_map.png","row_count":11,"width_value":32,"__class":"Sprite","height_value":32},{"col_count":13,"texture_name":"tile_map.png","row_count":11,"width_value":32,"__class":"Sprite","height_value":32},{"col_count":13,"texture_name":"tile_map.png","row_count":11,"width_value":32,"__class":"Sprite","height_value":32},{"col_count":13,"texture_name":"tile_map.png","row_count":11,"width_value":32,"__class":"Sprite","height_value":32},{"col_count":13,"texture_name":"tile_map.png","row_count":11,"width_value":32,"__class":"Sprite","height_value":32}],"height_value":32,"y_value":-13,"width_type":4,"y_type":4},{"__class":"Sprite","col_count":13,"height_value":32,"row_count":11,"y_value":377,"row_index":2,"width_value":32,"texture_name":"tile_map.png"},{"col_count":13,"height_value":32,"x_value":31,"row_index":2,"texture_name":"tile_map.png","row_count":11,"width_value":32,"y_value":346,"__class":"Sprite"},{"col_count":13,"row_count":11,"x_value":32,"y_value":377,"col_index":2,"texture_name":"tile_map.png","height_value":32,"width_value":32,"__class":"Sprite","row_index":2},{"col_count":13,"row_count":11,"x_value":63,"y_value":345,"col_index":2,"texture_name":"tile_map.png","height_value":32,"width_value":32,"__class":"Sprite","row_index":2},{"col_count":13,"__class":"Sprite","x_value":63,"y_value":314,"col_index":2,"texture_name":"tile_map.png","width_value":32,"height_value":32,"row_count":11},{"col_count":13,"row_count":11,"x_value":64,"y_value":377,"col_index":4,"texture_name":"tile_map.png","height_value":32,"width_value":32,"__class":"Sprite","row_index":2},{"col_count":13,"row_count":11,"x_value":96,"y_value":377,"col_index":5,"texture_name":"tile_map.png","height_value":32,"width_value":32,"__class":"Sprite","row_index":2},{"col_count":13,"row_count":11,"x_value":127,"y_value":377,"col_index":3,"texture_name":"tile_map.png","height_value":32,"width_value":32,"__class":"Sprite","row_index":2},{"col_count":13,"__class":"Sprite","x_value":514,"y_value":377,"col_index":5,"texture_name":"tile_map.png","width_value":32,"height_value":32,"row_count":11},{"col_count":13,"height_value":32,"x_value":418,"y_value":377,"col_index":3,"texture_name":"tile_map.png","width_value":32,"row_count":11,"__class":"Sprite"},{"col_count":13,"__class":"Sprite","x_value":482,"y_value":377,"col_index":4,"texture_name":"tile_map.png","width_value":32,"row_count":11,"height_value":32},{"col_count":13,"row_count":11,"x_value":450,"y_value":377,"col_index":4,"texture_name":"tile_map.png","width_value":32,"height_value":32,"__class":"Sprite"},{"col_count":13,"row_count":11,"x_value":95,"y_value":345,"col_index":3,"texture_name":"tile_map.png","height_value":32,"width_value":32,"__class":"Sprite","row_index":2},{"__class":"Image","y_value":377,"x_value":76,"width_value":32,"texture_name":"player_icon.png","height_value":32}],"width_type":4,"height_type":4},{"__extends":"title_item","__module":"SuperMarioBros","x_type":3},{"texture_name":"title.png","y_value":57,"__class":"Image","width_value":387,"x_type":3,"height_value":178},{"text":"develop By ALittle Engine","green":0.7843137254902,"__class":"Text","blue":0.72156862745098,"x_value":274,"y_value":236,"font_path":"ClearSans-Bold.ttf","font_size":20},{"text":"TOP-","__class":"Text","x_type":3,"x_value":-53,"y_value":336,"font_path":"ClearSans-Bold.ttf","font_size":20},{"font_path":"ClearSans-Bold.ttf","text":"00000000","__class":"Text","x_type":3,"x_value":27,"y_value":336,"__link":"_top_score","font_size":20},{"__link":"_startgame_text","text":"START GAME","__class":"Text","font_path":"ClearSans-Bold.ttf","x_value":-16,"y_value":269,"x_type":3,"font_size":20},{"font_path":"ClearSans-Bold.ttf","text":"EDIT WORLD","__class":"Text","x_type":3,"x_value":-17,"y_value":303,"__link":"_editworld_text","font_size":20},{"__class":"Image","x_type":3,"texture_name":"select_cursor.png","y_value":274,"x_value":-98,"width_value":16,"__link":"_select_cursor","height_value":16},{"text":"G:select H:confirm","__class":"Text","alpha":0.58823529411765,"font_path":"ClearSans-Bold.ttf","y_value":260,"x_type":4,"font_size":15},{"text":"J:speed up K:jump","__class":"Text","y_value":287,"font_path":"ClearSans-Bold.ttf","alpha":0.58823529411765,"x_type":4,"font_size":15},{"text":"A:left S:down D:right W:up","__class":"Text","alpha":0.58823529411765,"font_path":"ClearSans-Bold.ttf","y_value":312,"x_type":4,"font_size":15}],"height_value":460,"width_value":560},"flag_1":{"row_index":3,"col_count":13,"height_value":32,"texture_name":"tile_map.png","__class":"Sprite","width_value":32,"row_count":11,"col_index":4},"select_frame":{"__class":"DisplayLayout","__childs":[{"width_value":1,"__class":"Quad","height_type":4},{"x_type":4,"width_value":1,"__class":"Quad","height_type":4},{"height_value":1,"width_type":4,"__class":"Quad"},{"width_type":4,"__class":"Quad","height_value":1,"y_type":4}],"width_type":4,"height_type":4},"battle_scene":{"height_value":460,"__target_class":["SuperMarioBros","BattleScene"],"width_value":560,"__class":"DisplayLayout","__childs":[{"container":{"__extends":"scroll_container","__module":"SuperMarioBros"},"__class":"ScrollScreen","height_type":4,"__childs":[{"__class":"Linear","width_type":4,"__link":"_tile_linear","height_type":4},{"__class":"DisplayLayout","width_type":4,"__link":"_entity_container","height_type":4},{"__module":"SuperMarioBros","__extends":"player_1","y_value":219,"__link":"_player","x_value":17},{"__class":"DisplayLayout","width_type":4,"__link":"_effect_container","height_type":4}],"__link":"_scroll_screen","width_type":4},{"__extends":"title_item","__module":"SuperMarioBros"}]},"edit_scene":{"height_value":480,"__target_class":["SuperMarioBros","EditScene"],"width_value":1280,"__childs":[{"green":0.16862745098039,"__class":"Quad","height_type":4,"red":0.16862745098039,"width_type":4,"blue":0.16862745098039},{"__class":"DisplayLayout","height_type":4,"width_value":424,"width_type":4,"__childs":[{"__extends":"scroll_screen","__module":"SuperMarioBros","__link":"_scroll_screen","__childs":[{"green":0,"__class":"Quad","height_type":4,"red":0,"width_type":4,"blue":0},{"__link":"_tile_linear","width_type":4,"__class":"Linear","height_type":4},{"__link":"_entity_container","width_type":4,"__class":"DisplayLayout","height_type":4}]},{"height_value":20,"height_type":4,"__event":[{"type":"ALittle.UILButtonDownEvent","func":"HandleTileQuadClick"},{"type":"ALittle.UIButtonDragEvent","func":"HandleTileQuadDrag"}],"alpha":0,"width_type":4,"__class":"Quad"}]},{"x_type":4,"height_value":352,"__class":"Image","__event":[{"type":"ALittle.UILButtonDownEvent","func":"HandleTileSelected"}],"texture_name":"tile_map.png","width_value":416,"__link":"_tile_image","y_type":4},{"height_value":127,"__childs":[{"col_count":13,"__class":"TileTable","height_type":4,"__childs":[{"__extends":"random_wall_1","__module":"SuperMarioBros","__link":"_entity_random_wall_1"},{"__extends":"wall_1","__module":"SuperMarioBros","__link":"_entity_wall_1"},{"__extends":"enemy_1","__module":"SuperMarioBros","__link":"_entity_enemy_1"},{"__extends":"hide_wall_1","__module":"SuperMarioBros","__link":"_entity_hide_wall_1"},{"__extends":"enemy_2","__module":"SuperMarioBros","__link":"_entity_enemy_2","center_y":14},{"__extends":"flag_1","__module":"SuperMarioBros","__link":"_entity_flag_1"},{"__extends":"flag_2","__module":"SuperMarioBros","__link":"_entity_flag_2"},{"__extends":"flag_3","__module":"SuperMarioBros","__link":"_entity_flag_3"},{"__extends":"flag_4","__module":"SuperMarioBros","__link":"_entity_flag_4"},{"__extends":"flag_5","__module":"SuperMarioBros","__link":"_entity_flag_5"},{"__extends":"born_1","__module":"SuperMarioBros","__link":"_entity_born_1"}],"width_type":4},{"width_type":1,"disabled":true,"height_value":32,"height_type":1,"__extends":"select_frame","width_value":32,"__link":"_select_frame","__module":"SuperMarioBros"}],"width_type":4,"x_type":4,"height_type":4,"__class":"DisplayLayout","width_value":863,"__link":"_entity_panel","y_type":4},{"col_count":13,"__class":"Sprite","x_value":310,"y_value":68,"texture_name":"tile_map.png","__link":"_select_tile","row_count":11,"width_value":32,"x_type":4,"height_value":32},{"__class":"Text","underline":true,"x_value":863,"__event":[{"type":"ALittle.UILButtonDownEvent","func":"HandleSaveClick"}],"font_path":"ClearSans-Bold.ttf","text":"Save","y_value":4,"hand_cursor":true,"font_size":20},{"__class":"Text","underline":true,"x_value":929,"__event":[{"type":"ALittle.UILButtonDownEvent","func":"HandleBackClick"}],"font_path":"ClearSans-Bold.ttf","text":"Back","y_value":4,"hand_cursor":true,"font_size":20},{"text":"World","__class":"Text","x_value":1038,"y_value":4,"font_path":"ClearSans-Bold.ttf","font_size":20},{"text":"-","__class":"Text","x_value":1144,"y_value":4,"font_path":"ClearSans-Bold.ttf","font_size":20},{"text":"SELECT","__class":"Text","x_value":863,"y_value":67,"font_path":"ClearSans-Bold.ttf","font_size":20},{"__class":"Text","underline":true,"x_value":1099,"__event":[{"type":"ALittle.UILButtonDownEvent","func":"HandleTileTabClick"}],"font_path":"ClearSans-Bold.ttf","text":"TILE","y_value":94,"hand_cursor":true,"font_size":20},{"__class":"Text","underline":true,"x_value":1163,"__event":[{"type":"ALittle.UILButtonDownEvent","func":"HandleEntityTabClick"}],"font_path":"ClearSans-Bold.ttf","text":"ENTITY","y_value":94,"hand_cursor":true,"font_size":20},{"height_value":27,"x_value":137,"y_value":5,"font_path":"ClearSans-Bold.ttf","text":"1","x_type":4,"__event":[{"type":"ALittle.UILButtonDownEvent","func":"HandleWorldChanged"}],"__class":"TextInput","width_value":38,"__link":"_world_input","font_size":20},{"height_value":27,"x_value":61,"__event":[{"type":"ALittle.UIChangedEvent","func":"HandleWorldChanged"}],"font_path":"ClearSans-Bold.ttf","text":"1","y_value":5,"__class":"TextInput","x_type":4,"width_value":56,"__link":"_subworld_input","font_size":20}],"__class":"DisplayLayout"}}