{"tab_radio_button":{"height_value":22,"show_selected_disabled":{"height_type":1,"left_size":1,"height_value":22,"top_size":1,"width_value":50,"width_type":1,"right_size":3,"texture_name":"tab\/tab_radio_select.png","bottom_size":2,"__class":"Grid9Image"},"show_down":{"height_type":1,"left_size":1,"height_value":22,"top_size":1,"width_value":50,"width_type":1,"right_size":3,"texture_name":"tab\/tab_radio_up.png","bottom_size":2,"__class":"Grid9Image"},"show_up":{"height_type":1,"left_size":1,"height_value":22,"top_size":1,"width_value":50,"width_type":1,"right_size":3,"texture_name":"tab\/tab_radio_up.png","bottom_size":2,"__class":"Grid9Image"},"show_disabled":{"height_type":1,"left_size":1,"height_value":22,"top_size":1,"width_value":50,"width_type":1,"right_size":3,"texture_name":"tab\/tab_radio_up.png","bottom_size":2,"__class":"Grid9Image"},"show_selected_over":{"height_type":1,"left_size":1,"height_value":22,"top_size":1,"width_value":50,"width_type":1,"right_size":3,"texture_name":"tab\/tab_radio_select.png","bottom_size":2,"__class":"Grid9Image"},"show_selected_down":{"height_type":1,"left_size":1,"height_value":22,"top_size":1,"width_value":50,"width_type":1,"right_size":3,"texture_name":"tab\/tab_radio_select.png","bottom_size":2,"__class":"Grid9Image"},"__class":"TextRadioButton","show_selected_up":{"height_type":1,"left_size":1,"height_value":22,"top_size":1,"width_value":50,"width_type":1,"right_size":3,"texture_name":"tab\/tab_radio_select.png","bottom_size":2,"__class":"Grid9Image"},"show_over":{"height_type":1,"left_size":1,"height_value":22,"top_size":1,"width_value":50,"width_type":1,"right_size":3,"texture_name":"tab\/tab_radio_over.png","bottom_size":2,"__class":"Grid9Image"},"width_value":50}}