{"ide_setting_scrollbar_extend":{"height_value":155,"width_value":0,"__childs":[{"y_value":6,"x_value":6,"__extends":"usual_label","__module":"AUIPlugin","__module":"AUIPlugin","text":"总大小"},{"width_value":50,"__event":[{"type":"ALittle.UIEnterKeyEvent","func":"HandleTotleSizeFOCUSOUT"},{"type":"ALittle.UIFocusOutEvent","func":"HandleTotleSizeFOCUSOUT"}],"y_value":2,"__module":"AUIPlugin","__extends":"image_input","__module":"AUIPlugin","__link":"_total_size","x_value":57},{"y_value":5,"x_value":117,"__extends":"usual_label","__module":"AUIPlugin","__module":"AUIPlugin","text":"可见的大小"},{"width_value":50,"__event":[{"type":"ALittle.UIEnterKeyEvent","func":"HandleShowSizeFOCUSOUT"},{"type":"ALittle.UIFocusOutEvent","func":"HandleShowSizeFOCUSOUT"}],"y_value":2,"__module":"AUIPlugin","__extends":"image_input","__module":"AUIPlugin","__link":"_show_size","x_value":184},{"y_value":31,"x_value":6,"__extends":"usual_label","__module":"AUIPlugin","__module":"AUIPlugin","text":"偏移大小"},{"width_value":50,"__event":[{"type":"ALittle.UIEnterKeyEvent","func":"HandleOffsetRateFOCUSOUT"},{"type":"ALittle.UIFocusOutEvent","func":"HandleOffsetRateFOCUSOUT"}],"y_value":27,"__module":"AUIPlugin","__extends":"image_input","__module":"AUIPlugin","__link":"_offset_rate","x_value":57},{"y_value":30,"x_value":117,"__extends":"usual_label","__module":"AUIPlugin","__module":"AUIPlugin","text":"偏移步长"},{"width_value":50,"__event":[{"type":"ALittle.UIEnterKeyEvent","func":"HandleOffsetStepFOCUSOUT"},{"type":"ALittle.UIFocusOutEvent","func":"HandleOffsetStepFOCUSOUT"}],"y_value":27,"__module":"AUIPlugin","__extends":"image_input","__module":"AUIPlugin","__link":"_offset_step","x_value":184},{"y_value":57,"x_value":4,"__extends":"usual_label","__module":"AUIPlugin","__module":"AUIPlugin","text":"头部按钮"},{"width_value":150,"__event":[{"type":"ALittle.UIEnterKeyEvent","func":"HandleUpButtonFOCUSOUT"},{"type":"ALittle.UIFocusOutEvent","func":"HandleUpButtonFOCUSOUT"},{"type":"ALittle.UIFocusInEvent","func":"HandleCommonInputFOCUSIN"}],"y_value":55,"__module":"AUIPlugin","__extends":"image_input","__module":"AUIPlugin","__link":"_up_button","x_value":56},{"y_value":80,"x_value":4,"__extends":"usual_label","__module":"AUIPlugin","__module":"AUIPlugin","text":"尾部按钮"},{"width_value":150,"__event":[{"type":"ALittle.UIEnterKeyEvent","func":"HandleDownButtonFOCUSOUT"},{"type":"ALittle.UIFocusOutEvent","func":"HandleDownButtonFOCUSOUT"},{"type":"ALittle.UIFocusInEvent","func":"HandleCommonInputFOCUSIN"}],"y_value":80,"__module":"AUIPlugin","__extends":"image_input","__module":"AUIPlugin","__link":"_down_button","x_value":56},{"y_value":106,"x_value":4,"__extends":"usual_label","__module":"AUIPlugin","__module":"AUIPlugin","text":"拖拽按钮"},{"width_value":150,"__event":[{"type":"ALittle.UIEnterKeyEvent","func":"HandleBarButtonFOCUSOUT"},{"type":"ALittle.UIFocusOutEvent","func":"HandleBarButtonFOCUSOUT"},{"type":"ALittle.UIFocusInEvent","func":"HandleCommonInputFOCUSIN"}],"y_value":105,"__module":"AUIPlugin","__extends":"image_input","__module":"AUIPlugin","__link":"_bar_button","x_value":56},{"text":"背景图片","__event":[{"type":"ALittle.UILButtonDownEvent","func":"HandleBarBackSelect"}],"underline":true,"y_value":132,"__module":"AUIPlugin","__extends":"usual_label","__module":"AUIPlugin","hand_cursor":true,"x_value":4},{"width_value":100,"__event":[{"type":"ALittle.UIEnterKeyEvent","func":"HandleBarBackFOCUSOUT"},{"type":"ALittle.UIFocusOutEvent","func":"HandleBarBackFOCUSOUT"},{"type":"ALittle.UIFocusInEvent","func":"HandleCommonInputFOCUSIN"}],"y_value":130,"__module":"AUIPlugin","__extends":"image_input","__module":"AUIPlugin","__link":"_bar_background","x_value":56},{"x_value":160,"__event":[{"type":"ALittle.UIChangedEvent","func":"HandleBarBackFOCUSOUT"}],"y_value":131,"__module":"AUIPlugin","__extends":"usual_check_button","__module":"AUIPlugin","__link":"_bar_background_grid9","text":"九宫格"}],"width_type":4,"__class":"DisplayLayout"}}