{"ide_new_project_dialog":{"title":"新建项目","height_value":188,"width_value":337,"__childs":[{"x_value":113,"__link":"_default_font_size","y_value":96,"width_value":200,"__extends":"ide_common_image_input","__module":"AUIPlugin","text":"30"},{"y_value":100,"text":"默认字体大小：","__extends":"ide_common_tab_text_selected","__module":"AUIPlugin","x_value":25},{"x_value":113,"__link":"_default_font_path","y_value":71,"width_value":200,"__extends":"ide_common_image_input","__module":"AUIPlugin","text":"fzcyjt.ttf"},{"y_value":75,"text":"默认字体路径：","__extends":"ide_common_tab_text_selected","__module":"AUIPlugin","x_value":25},{"text":"项目名称：","y_value":20,"x_value":48,"__extends":"ide_common_tab_text_selected","__module":"AUIPlugin","description":"项目名称："},{"description":"项目名输入框","__link":"_project_new_name","width_value":200,"y_value":16,"__extends":"ide_common_image_input","__module":"AUIPlugin","x_value":113},{"__extends":"ide_common_usual_button","__module":"AUIPlugin","text":"取消","y_type":4,"y_value":10,"description":"取消","x_type":3,"__event":[{"type":"ALittle.UIClickEvent","func":"HandleNewProjectCancel"}],"x_value":-60},{"__extends":"ide_common_usual_button","__module":"AUIPlugin","text":"确定","y_type":4,"y_value":10,"description":"确定","x_type":3,"__event":[{"type":"ALittle.UIClickEvent","func":"HandleNewProjectConfirm"}],"x_value":60},{"data_list":["1280x720","720x1280","1366x750","750x1366","1280x900"],"width_value":198,"y_value":45.5,"__link":"_view_size_dropdown","__extends":"ide_common_dropdown","__module":"AUIPlugin","x_value":113},{"text":"窗口大小：","y_value":48,"x_value":48,"__extends":"ide_common_tab_text_selected","__module":"AUIPlugin","description":"项目名称："}],"__extends":"ide_common_dialog_with_close","__module":"AUIPlugin","description":"新建项目对话框"}}