{"ide_setting_displaylayout_base2":{"__class":"DisplayLayout","width_type":4,"__childs":[{"y_value":52.5,"__module":"AUIPlugin","text":"描述","__extends":"usual_label","x_value":16},{"__link":"_description","__module":"AUIPlugin","__extends":"image_input","__event":[{"type":"ALittle.UIEnterKeyEvent","func":"HandleDescriptionFOCUSOUT"},{"type":"ALittle.UIFocusOutEvent","func":"HandleDescriptionFOCUSOUT"},{"type":"ALittle.UITabKeyEvent","func":"HandleDescriptionTabKey"}],"width_value":200,"y_value":51,"x_value":45},{"y_value":5.875,"__module":"AUIPlugin","text":"  A  ","__extends":"usual_label","__event":[{"type":"ALittle.UIButtonDragEvent","func":"HandleAlphaValueDrag"},{"type":"ALittle.UIMoveInEvent","func":"HandleAlphaValueMoveIn"},{"type":"ALittle.UIMoveOutEvent","func":"HandleAlphaValueMoveOut"}],"x_value":187},{"__link":"_alpha","__module":"AUIPlugin","__extends":"image_input","__event":[{"type":"ALittle.UIEnterKeyEvent","func":"HandleAlphaFOCUSOUT"},{"type":"ALittle.UIFocusOutEvent","func":"HandleAlphaFOCUSOUT"},{"type":"ALittle.UITabKeyEvent","func":"HandleAlphaValueTabKey"}],"width_value":35,"y_value":2.875,"x_value":210},{"y_value":5.875,"__module":"AUIPlugin","text":"  R  ","__extends":"usual_label","__event":[{"type":"ALittle.UIButtonDragEvent","func":"HandleRedValueDrag"},{"type":"ALittle.UIMoveInEvent","func":"HandleRedValueMoveIn"},{"type":"ALittle.UIMoveOutEvent","func":"HandleRedValueMoveOut"}],"x_value":2},{"__link":"_red","__module":"AUIPlugin","__extends":"image_input","__event":[{"type":"ALittle.UIEnterKeyEvent","func":"HandleRedFOCUSOUT"},{"type":"ALittle.UIFocusOutEvent","func":"HandleRedFOCUSOUT"},{"type":"ALittle.UITabKeyEvent","func":"HandleRedValueTabKey"}],"width_value":35,"y_value":2.875,"x_value":26},{"y_value":5.875,"__module":"AUIPlugin","text":"  G  ","__extends":"usual_label","__event":[{"type":"ALittle.UIButtonDragEvent","func":"HandleGreenValueDrag"},{"type":"ALittle.UIMoveInEvent","func":"HandleGreenValueMoveIn"},{"type":"ALittle.UIMoveOutEvent","func":"HandleGreenValueMoveOut"}],"x_value":63},{"__link":"_green","__module":"AUIPlugin","__extends":"image_input","__event":[{"type":"ALittle.UIEnterKeyEvent","func":"HandleGreenFOCUSOUT"},{"type":"ALittle.UIFocusOutEvent","func":"HandleGreenFOCUSOUT"},{"type":"ALittle.UITabKeyEvent","func":"HandleGreenValueTabKey"}],"width_value":35,"y_value":2.875,"x_value":86},{"y_value":5.875,"__module":"AUIPlugin","text":"  B  ","__extends":"usual_label","__event":[{"type":"ALittle.UIButtonDragEvent","func":"HandleBlueValueDrag"},{"type":"ALittle.UIMoveInEvent","func":"HandleBlueValueMoveIn"},{"type":"ALittle.UIMoveOutEvent","func":"HandleBlueValueMoveOut"}],"x_value":124},{"__link":"_blue","__module":"AUIPlugin","__extends":"image_input","__event":[{"type":"ALittle.UIEnterKeyEvent","func":"HandleBlueFOCUSOUT"},{"type":"ALittle.UIFocusOutEvent","func":"HandleBlueFOCUSOUT"},{"type":"ALittle.UITabKeyEvent","func":"HandleBlueValueTabKey"}],"width_value":35,"y_value":2.875,"x_value":147},{"y_value":28.944444444447,"__module":"AUIPlugin","hand_cursor":true,"text":"手型","__extends":"usual_label","__link":"_hand_cursor_check_text","x_value":28.33333333333},{"__link":"_hand_cursor","__module":"AUIPlugin","x_value":11,"__event":[{"type":"ALittle.UIChangedEvent","func":"HandleHandCursorChanged"}],"y_value":31.944444444447,"__extends":"check_button"},{"y_value":28.944444444447,"__module":"AUIPlugin","hand_cursor":true,"text":"显示","__extends":"usual_label","__link":"_visible_check_text","x_value":81.33333333333},{"__link":"_visible","__module":"AUIPlugin","__extends":"check_button","y_value":31.944444444447,"__event":[{"type":"ALittle.UIChangedEvent","func":"HandleVisibleChanged"}],"x_value":61},{"y_value":28.944444444447,"__module":"AUIPlugin","hand_cursor":true,"text":"禁用","__extends":"usual_label","__link":"_disabled_check_text","x_value":131.33333333333},{"__link":"_disabled","__module":"AUIPlugin","x_value":112,"__event":[{"type":"ALittle.UIChangedEvent","func":"HandleDisabledChanged"}],"y_value":31.944444444447,"__extends":"check_button"},{"y_value":102,"__module":"AUIPlugin","text":"绑定","__extends":"usual_label","x_value":16},{"__link":"___link","__module":"AUIPlugin","__extends":"image_input","__event":[{"type":"ALittle.UIFocusOutEvent","func":"HandleLinkFOCUSOUT"},{"type":"ALittle.UITabKeyEvent","func":"HandleLinkTabKey"},{"type":"ALittle.UIChangedEvent","func":"HandleLinkChanged"}],"width_value":175,"y_value":101,"x_value":45},{"y_value":126.609375,"__module":"AUIPlugin","__extends":"image_input","__link":"___event","width_value":146,"disabled":true,"x_value":45},{"y_value":78.5,"__module":"AUIPlugin","text":"插件类","__extends":"usual_label","x_value":4},{"__link":"___target_class","__module":"AUIPlugin","__extends":"image_input","__event":[{"type":"ALittle.UIFocusOutEvent","func":"HandleTargetClassFOCUSOUT"},{"type":"ALittle.UITabKeyEvent","func":"HandleTargetClassTabKey"},{"type":"ALittle.UIChangedEvent","func":"HandleTargetClassChanged"}],"width_value":175,"y_value":76,"x_value":45},{"y_value":129.609375,"__module":"AUIPlugin","text":"事件","__extends":"usual_label","x_value":16},{"y_value":127.109375,"__module":"AUIPlugin","text":"设置","__extends":"usual_button","__event":[{"type":"ALittle.UIClickEvent","func":"HandleEventFOCUSOUT"}],"x_value":192},{"__event":[{"type":"ALittle.UIClickEvent","func":"HandleTargetClassEditClick"}],"__module":"AUIPlugin","x_value":221,"text":"Go","width_value":24,"y_value":77.109375000001,"__extends":"usual_button"},{"__event":[{"type":"ALittle.UIClickEvent","func":"HandleLinkEditClick"}],"__module":"AUIPlugin","__extends":"usual_button","text":"Go","width_value":24,"y_value":102.109375,"x_value":221}],"height_value":152}}