{"ide_find_file_dialog":{"x_type":1,"title":"查找文件","width_value":702,"y_type":1,"__extends":"dialog_with_close","__childs":[{"x_value":9,"width_type":4,"width_value":82,"y_value":4.75,"__extends":"image_input","__link":"_find_input","__module":"AUIPlugin","__event":[{"type":"ALittle.UIEnterKeyEvent","func":"HandleEnterKeyClick"}]},{"x_type":4,"x_value":12,"__event":[{"type":"ALittle.UIClickEvent","func":"HandleSearchClick"}],"__extends":"usual_button","text":"搜索","__module":"AUIPlugin","y_value":4.25},{"x_type":3,"width_type":4,"height_type":4,"__link":"_file_scroll_screen","y_value":9,"height_value":43,"y_type":4,"__class":"ScrollScreen","width_value":16,"__module":"AUIPlugin","__extends":"scroll_screen_v"}],"__module":"AUIPlugin","height_value":368}}