{"ide_main_scene":{"__childs":[{"__class":"Grid3","height_value":0,"description":"主界面","up_size":33,"show_center":{"height_type":4,"width_type":4,"__childs":[{"show_center":{"up_size":440,"__class":"Grid3","show_up":{"__childs":[{"blue":0.14901960784314,"green":0.14509803921569,"__class":"Quad","width_type":4,"height_type":4,"red":0.14509803921569},{"width_value":3,"__class":"Quad","x_type":4,"__event":[{"type":"ALittle.UIMoveInEvent","func":"System_SetHDragCursor","logic":["ALittle"]},{"func":"HandleLeftEditResizeDrag","type":"ALittle.UIButtonDragEvent"},{"type":"ALittle.UIMoveOutEvent","func":"System_SetNormalCursor","logic":["ALittle"]}],"height_value":0,"alpha":0,"height_type":4},{"height_type":4,"height_value":0,"__link":"_control_edit_grid3","width_value":3,"show_center":{"__class":"DisplayLayout","__childs":[{"alpha":0,"__class":"Quad","__event":[{"type":"ALittle.UIMoveInEvent","func":"System_SetVDragCursor","logic":["ALittle"]},{"func":"HandleControlEditResizeDrag","type":"ALittle.UIButtonDragEvent"},{"type":"ALittle.UIMoveOutEvent","func":"System_SetNormalCursor","logic":["ALittle"]}],"height_value":3,"width_type":4,"width_value":0},{"blue":0.14901960784314,"green":0.14509803921569,"__class":"Quad","x_value":1,"red":0.14509803921569,"height_value":25,"width_type":4,"y_value":3},{"__extends":"tab","height_type":4,"y_type":4,"__childs":[{"width_value":400,"__class":"DisplayLayout","__target_class":["ALittleIDE","IDEUIControlList"],"__childs":[{"__class":"Grid3","height_value":23,"y_value":5,"show_down":{"text":"搜索","__extends":"usual_button","__event":[{"func":"HandleControlSearchClick","type":"ALittle.UIClickEvent"}],"__module":"AUIPlugin"},"width_value":10,"down_size":52,"show_center":{"type":1,"__class":"Grid3","show_center":{"__event":[{"func":"HandleControlSearchClick","type":"ALittle.UIEnterKeyEvent"},{"func":"HandleControlSearchClick","type":"ALittle.UIChangedEvent"}],"__extends":"image_input","__module":"AUIPlugin","__link":"_control_search_key"},"gap":1,"width_type":4,"height_type":4},"gap":2,"width_type":4,"type":1,"x_type":3},{"__extends":"scroll_screen","height_type":4,"y_type":4,"height_value":38,"y_value":5,"width_value":10,"x_type":3,"width_type":4,"__link":"_control_scroll_screen","__module":"AUIPlugin"}],"height_value":400,"description":"控件库","__link":"_control_list"},{"width_value":400,"__class":"DisplayLayout","__target_class":["ALittleIDE","IDEUICodeList"],"__childs":[{"__class":"Grid3","height_value":23,"y_value":5,"show_down":{"text":"搜索","__extends":"usual_button","__event":[{"func":"HandleCodeSearchClick","type":"ALittle.UIClickEvent"}],"__module":"AUIPlugin"},"width_value":10,"down_size":52,"show_center":{"type":1,"__class":"Grid3","show_center":{"__event":[{"func":"HandleCodeSearchClick","type":"ALittle.UIEnterKeyEvent"},{"func":"HandleCodeSearchClick","type":"ALittle.UIChangedEvent"}],"__extends":"image_input","__module":"AUIPlugin","__link":"_code_search_key"},"gap":1,"width_type":4,"height_type":4},"gap":2,"width_type":4,"type":1,"x_type":3},{"__extends":"scroll_screen","__class":"ScrollScreen","y_type":4,"height_value":38,"__link":"_code_scroll_screen","width_value":10,"height_type":4,"x_type":3,"width_type":4,"y_value":5,"__module":"AUIPlugin"}],"height_value":400,"description":"代码库","__link":"_code_list"},{"__class":"DisplayLayout","__childs":[{"__extends":"file_tree_layout","x_type":3,"y_type":3,"height_value":10,"__link":"_tile_list","width_value":10,"__target_class":["ALittleIDE","IDEUITileList"],"__module":"AUIPlugin"}],"width_type":4,"description":"地图库","height_type":4},{"__extends":"ide_tile_detail_layout","__link":"_tile_brush_list","__target_class":["ALittleIDE","IDEUITileBrushList"],"description":"地块库","__module":"ALittleIDE"},{"width_value":400,"__class":"DisplayLayout","__target_class":["ALittleIDE","IDEUIProjectList"],"__childs":[{"__class":"Grid3","height_value":23,"y_value":5,"show_down":{"text":"搜索","__extends":"usual_button","__event":[{"func":"HandleProjectSearchClick","type":"ALittle.UIClickEvent"}],"__module":"AUIPlugin"},"width_value":10,"down_size":52,"show_center":{"__event":[{"func":"HandleProjectSearchClick","type":"ALittle.UIEnterKeyEvent"}],"__extends":"image_input","__module":"AUIPlugin","__link":"_project_search_key"},"gap":2,"width_type":4,"type":1,"x_type":3},{"__extends":"scroll_screen","height_type":4,"y_type":4,"height_value":38,"y_value":5,"width_value":10,"container":{"__extends":"scroll_screen_linear","__module":"AUIPlugin"},"x_type":3,"width_type":4,"__link":"_project_scroll_screen","__module":"AUIPlugin"}],"height_value":400,"description":"项目库","__link":"_project_list"}],"height_value":3,"__link":"_project_edit_tab","width_value":0,"width_type":4,"__module":"AUIPlugin"}]},"show_up":{"__class":"DisplayLayout","__childs":[{"blue":0.14901960784314,"green":0.14509803921569,"__class":"Quad","x_value":1,"width_type":4,"red":0.14509803921569,"height_value":25},{"__link":"_detail_tree_tab","width_value":0,"height_type":4,"y_type":4,"__childs":[{"__extends":"ide_control_detail_layout","__link":"_control_tree","__target_class":["ALittleIDE","IDEUIControlTree"],"description":"控件树","__module":"ALittleIDE"},{"__extends":"ide_brush_detail_layout","__module":"ALittleIDE","description":"笔刷","__link":"_tile_brush_edit"}],"width_type":4,"__extends":"tab","__module":"AUIPlugin"}]},"type":2,"width_type":4,"__class":"Grid3","up_size":350}],"width_type":4,"__class":"DisplayLayout","height_type":4},"show_center":{"__class":"DisplayLayout","__childs":[{"show_center":{"height_type":4,"width_type":4,"__childs":[{"blue":0.11764705882353,"green":0.11764705882353,"__class":"Quad","height_type":4,"width_type":4,"red":0.11764705882353,"__link":"_main_tab_bg"},{"blue":0.14901960784314,"green":0.14509803921569,"__class":"Quad","height_value":25,"width_type":4,"red":0.14509803921569},{"__extends":"tab","height_type":4,"height_value":0,"__link":"_main_tab","width_value":0,"view_margin":20,"width_type":4,"__module":"AUIPlugin"},{"x_value":3,"__extends":"ide_tab_right_button","x_type":4,"__event":[{"func":"HandleTabRightExMenu","type":"ALittle.UIClickEvent"}],"y_value":6}],"__target_class":["ALittleIDE","IDEContentEdit"],"__class":"DisplayLayout","__link":"_content_edit"},"height_type":4,"__class":"Grid3","show_down":{"__childs":[{"blue":0.11764705882353,"green":0.11764705882353,"__class":"Quad","width_type":4,"height_type":4,"red":0.11764705882353},{"blue":0.14901960784314,"green":0.14509803921569,"__class":"Quad","height_value":25,"width_type":4,"red":0.14509803921569},{"alpha":0,"__class":"Quad","__event":[{"type":"ALittle.UIMoveInEvent","func":"System_SetVDragCursor","logic":["ALittle"]},{"func":"HandleQuickEditResizeDrag","type":"ALittle.UIButtonDragEvent"},{"type":"ALittle.UIMoveOutEvent","func":"System_SetNormalCursor","logic":["ALittle"]}],"height_value":3,"width_type":4,"width_value":0},{"__link":"_project_quick_tab","width_value":0,"height_type":4,"y_type":4,"__childs":[{"height_type":4,"__class":"DisplayLayout","width_type":4,"__target_class":["ALittleIDE","IDEUIControlAnti"],"description":"动画编辑器","__link":"_control_anti"}],"width_type":4,"__extends":"tab","__module":"AUIPlugin"},{"__class":"TextCheckButton","height_value":15,"y_value":6.5,"x_value":3,"selected":true,"__event":[{"func":"HandleQuickFoldChanged","type":"ALittle.UIChangedEvent"}],"show_selected_up":{"__class":"Image","texture_name":"fold_down.png"},"show_selected_down":{"__class":"Image","texture_name":"fold_down.png"},"show_over":{"__class":"Image","texture_name":"fold_up.png"},"__link":"_quick_fold_updown","show_selected_over":{"__class":"Image","texture_name":"fold_down.png"},"x_type":4,"show_disabled":{"__class":"Image","texture_name":"fold_up.png"},"show_down":{"__class":"Image","texture_name":"fold_up.png"},"show_up":{"__class":"Image","texture_name":"fold_up.png"},"width_value":18,"show_selected_disabled":{"__class":"Image","texture_name":"fold_down.png"}}],"width_type":4,"__class":"DisplayLayout","height_type":4},"width_type":4,"down_size":250,"__link":"_quick_edit_grid3"}]},"type":1,"__link":"_right_edit_grid3"},"up_size":35,"__class":"Grid3","show_up":{"__class":"DisplayLayout","__childs":[{"blue":0.2,"green":0.2,"__class":"Quad","width_type":4,"height_type":4,"red":0.2},{"height_type":4,"__childs":[{"__extends":"usual_status_button","y_type":3,"height_value":25,"__link":"_tool_singleselect","x_value":8,"selected":true,"__event":[{"func":"HandleToolSingleSelect","type":"ALittle.UIChangedEvent"}],"group_name":"idetoolbutton201602011338","width_value":30,"__module":"AUIPlugin"},{"x_value":15,"width_value":17,"__class":"Image","y_type":3,"height_value":14,"texture_name":"tool_move.png","disabled":true},{"__extends":"usual_status_button","y_type":3,"height_value":25,"__link":"_tool_handdrag","x_value":38,"width_value":30,"__event":[{"func":"HandleToolHandDrag","type":"ALittle.UIChangedEvent"}],"group_name":"idetoolbutton201602011338","__module":"AUIPlugin"},{"x_value":44,"width_value":17,"__class":"Image","y_type":3,"height_value":17,"texture_name":"tool_hold.png","disabled":true},{"__extends":"usual_status_button","y_type":3,"height_value":25,"__link":"_tool_presee","x_value":69,"width_value":30,"__event":[{"func":"HandleToolPreSee","type":"ALittle.UIChangedEvent"}],"group_name":"idetoolbutton201602011338","__module":"AUIPlugin"},{"x_value":77,"width_value":12,"__class":"Image","y_type":3,"height_value":10,"texture_name":"tool_presee.png","disabled":true},{"x_value":143,"__extends":"tool_button","__module":"AUIPlugin","y_type":3,"__event":[{"func":"HandleToolHLAlign","type":"ALittle.UIClickEvent"}],"height_value":25,"width_value":25,"__link":"_tool_h_align_left"},{"height_type":1,"y_type":3,"height_value":15,"__link":"_tool_h_align_left_icon","x_value":149.75,"width_value":13,"disabled":true,"width_type":1,"texture_name":"hl_align.png","__class":"Image"},{"__extends":"usual_status_button","y_type":3,"height_value":25,"__link":"_tool_scale","x_value":99,"width_value":30,"__event":[{"func":"HandleToolScale","type":"ALittle.UIChangedEvent"}],"group_name":"idetoolbutton201602011338","__module":"AUIPlugin"},{"x_value":107,"width_value":16,"__class":"Image","y_type":3,"height_value":17,"texture_name":"tool_scale.png","disabled":true},{"x_value":170,"__extends":"tool_button","__module":"AUIPlugin","y_type":3,"__event":[{"func":"HandleToolHLAlign","type":"ALittle.UIClickEvent"}],"height_value":25,"width_value":25,"__link":"_tool_h_align_center"},{"height_type":1,"y_type":3,"height_value":17,"__link":"_tool_h_align_center_icon","x_value":177,"width_value":11,"disabled":true,"width_type":1,"texture_name":"hc_align.png","__class":"Image"},{"x_value":196,"__extends":"tool_button","__module":"AUIPlugin","y_type":3,"__event":[{"func":"HandleToolHLAlign","type":"ALittle.UIClickEvent"}],"height_value":25,"width_value":25,"__link":"_tool_h_align_right"},{"height_type":1,"y_type":3,"height_value":15,"__link":"_tool_h_align_right_icon","x_value":202,"width_value":13,"disabled":true,"width_type":1,"texture_name":"hr_align.png","__class":"Image"},{"x_value":224,"__extends":"tool_button","__module":"AUIPlugin","y_type":3,"__event":[{"func":"HandleToolHLAlign","type":"ALittle.UIClickEvent"}],"height_value":25,"width_value":25,"__link":"_tool_v_align_top"},{"__class":"Image","y_type":3,"height_value":14,"__link":"_tool_v_align_top_icon","x_value":230,"texture_name":"vt_align.png","height_type":1,"y_value":1,"disabled":true,"width_type":1,"width_value":14},{"x_value":252,"__extends":"tool_button","__module":"AUIPlugin","y_type":3,"__event":[{"func":"HandleToolHLAlign","type":"ALittle.UIClickEvent"}],"height_value":25,"width_value":25,"__link":"_tool_v_align_center"},{"__class":"Image","y_type":3,"height_value":12,"__link":"_tool_v_align_center_icon","x_value":257,"texture_name":"vc_align.png","height_type":1,"y_value":1,"disabled":true,"width_type":1,"width_value":16},{"x_value":279.25,"__extends":"tool_button","__module":"AUIPlugin","y_type":3,"__event":[{"func":"HandleToolHLAlign","type":"ALittle.UIClickEvent"}],"height_value":25,"width_value":25,"__link":"_tool_v_align_bottom"},{"__class":"Image","y_type":3,"height_value":14,"__link":"_tool_v_align_bottom_icon","x_value":284.75,"texture_name":"vb_align.png","height_type":1,"y_value":1,"disabled":true,"width_type":1,"width_value":14},{"x_value":200,"__extends":"image_input","__module":"AUIPlugin","visible":false,"__event":[{"func":"HandleToolScaleInputFOCUSOUT","type":"ALittle.UIEnterKeyEvent"},{"func":"HandleToolScaleInputFOCUSOUT","type":"ALittle.UIFocusOutEvent"}],"__link":"_tool_scale_input","width_value":57,"y_value":8.5},{"text":"缩放比例","__extends":"usual_label","__module":"AUIPlugin","visible":false,"__event":[{"func":"HandleToolScaleDrag","type":"ALittle.UIButtonDragEvent"},{"func":"HandleToolScaleMoveIn","type":"ALittle.UIMoveInEvent"},{"func":"HandleToolScaleMoveOut","type":"ALittle.UIMoveOutEvent"}],"x_value":150,"__link":"_tool_scale_text","y_value":11.5}],"width_type":4,"__class":"DisplayLayout","__link":"_tool_ui_container"},{"height_type":4,"__childs":[{"text":"向前","__extends":"usual_button","y_type":3,"y_value":0.5,"x_value":5,"width_value":36,"__event":[{"func":"HandleJumpPreCodeClick","type":"ALittle.UIClickEvent"}],"__link":"_tool_jumpprecode","__module":"AUIPlugin"},{"text":"向后","__extends":"usual_button","y_type":3,"y_value":0.5,"x_value":43,"width_value":36,"__event":[{"func":"HandleJumpNextCodeClick","type":"ALittle.UIClickEvent"}],"__link":"_tool_jumpnextcode","__module":"AUIPlugin"},{"text":"Lua","__extends":"dropdown","y_type":3,"__link":"_tool_language","x_value":152.5,"width_value":103,"data_list":["Lua","JavaScript"],"__event":[{"func":"HandleTargetLanguageSelectChange","type":"ALittle.UISelectChangedEvent"}],"y_value":0.5,"__module":"AUIPlugin"},{"text":"目标语言:","__extends":"usual_label","y_type":3,"y_value":0.5,"x_value":98,"__module":"AUIPlugin"}],"width_type":4,"__class":"DisplayLayout","__link":"_tool_code_container"},{"height_type":4,"__childs":[{"__extends":"usual_status_button","y_type":3,"height_value":25,"__link":"_tool_tile_brush","x_value":8,"selected":true,"__event":[{"func":"HandleToolTileBrushSelect","type":"ALittle.UIChangedEvent"}],"group_name":"idetoolbutton201602011338","width_value":30,"__module":"AUIPlugin"},{"x_value":15,"texture_name":"brush.png","__class":"Image","y_type":3,"height_value":20,"width_value":20,"disabled":true},{"__extends":"usual_status_button","y_type":3,"height_value":25,"__link":"_tool_tile_handdrag","x_value":38,"width_value":30,"__event":[{"func":"HandleToolTileHandDrag","type":"ALittle.UIChangedEvent"}],"group_name":"idetoolbutton201602011338","__module":"AUIPlugin"},{"x_value":44,"texture_name":"tool_hold.png","__class":"Image","y_type":3,"height_value":17,"width_value":17,"disabled":true},{"__extends":"usual_status_button","y_type":3,"height_value":25,"__link":"_tool_tile_erase","x_value":69,"width_value":30,"__event":[{"func":"HandleToolTileErase","type":"ALittle.UIChangedEvent"}],"group_name":"idetoolbutton201602011338","__module":"AUIPlugin"},{"x_value":77,"texture_name":"Erase.png","__class":"Image","y_type":3,"height_value":16,"width_value":16,"disabled":true}],"width_type":4,"__class":"DisplayLayout","__link":"_tool_tile_container"},{"text":"代码搜索","__extends":"usual_button","x_type":4,"y_type":3,"__event":[{"func":"HandleFindFileClick","type":"ALittle.UIClickEvent"}],"x_value":67,"width_value":66,"__module":"AUIPlugin"},{"x_value":8,"__extends":"usual_button","x_type":4,"y_type":3,"__event":[{"func":"HandleImageSelectClick","type":"ALittle.UIClickEvent"}],"text":"图片库","__module":"AUIPlugin"}]},"height_type":4,"width_type":4,"type":2,"__link":"_ui_edit_container"}],"__target_class":["ALittleIDE","IDEUICenter"],"__class":"DisplayLayout","__link":"_center"},"show_up":{"__class":"DisplayLayout","__childs":[{"blue":0.23921568627451,"green":0.23529411764706,"__class":"Quad","width_type":4,"height_type":4,"red":0.23529411764706},{"height_type":4,"y_type":3,"__childs":[{"text":"项目","__extends":"usual_menu_button","__event":[{"func":"HandleFileMenuClick","type":"ALittle.UIClickEvent"}],"__module":"AUIPlugin"},{"text":"编辑","__extends":"usual_menu_button","__event":[{"func":"HandleEditMenuClick","type":"ALittle.UIClickEvent"}],"__module":"AUIPlugin"},{"text":"运行","__extends":"usual_menu_button","__event":[{"func":"HandleRunMenuClick","type":"ALittle.UIClickEvent"}],"__module":"AUIPlugin"},{"text":"工具","__extends":"usual_menu_button","__event":[{"func":"HandleToolMenuClick","type":"ALittle.UIClickEvent"}],"__module":"AUIPlugin"},{"text":"帮助","__extends":"usual_menu_button","__event":[{"func":"HandleHelpMenuClick","type":"ALittle.UIClickEvent"}],"__module":"AUIPlugin"}],"__target_class":["ALittleIDE","IDEUIMainMenu"],"__link":"_main_menu","x_value":38,"type":1,"gap":1,"__class":"Linear"},{"width_value":141,"height_type":4,"x_type":4,"__childs":[{"__extends":"dropdown","x_type":4,"y_type":3,"__link":"_account_dropdown","x_value":4,"width_value":97,"data_list":["登录"],"visible":false,"__event":[{"func":"HandleAccountDropdownChange","type":"ALittle.UISelectChangedEvent"}],"__module":"AUIPlugin"},{"x_value":53,"width_value":17,"__class":"Image","y_type":3,"texture_name":"head_icon.png","height_value":17,"x_type":4,"__link":"_account_icon"},{"text":"请登录","__class":"Text","y_type":3,"font_size":13,"__link":"_account_login","font_path":"Miui-Regular.ttf","underline":true,"__event":[{"func":"HandleAccountLoginLB","type":"ALittle.UILButtonDownEvent"}],"x_type":4,"x_value":6,"hand_cursor":true}],"__target_class":["ALittleIDE","IDEUIAccount"],"__class":"DisplayLayout","__link":"_account"},{"width_type":4,"width_value":987,"height_type":4,"x_type":3,"__childs":[{"text":"当前没有打开的项目","__extends":"dropdown","x_type":3,"y_type":3,"__event":[{"func":"HandlePeojectSelectChange","type":"ALittle.UISelectChangedEvent"}],"__module":"AUIPlugin","width_value":201,"__link":"_current_project_name"}],"__target_class":["ALittleIDE","IDEUIProjectDropdown"],"__class":"DisplayLayout","__link":"_project_dropdown"},{"x_value":2,"texture_name":"small_icon.png","__class":"Image","y_type":3,"height_value":30,"width_value":30}]},"width_value":0,"width_type":4,"type":2,"height_type":4}],"width_type":4,"__class":"DisplayLayout","height_type":4}}