{"player_1":{"height_value":64,"__childs":[{"height_value":32,"texture_name":"player1_level_1_right.png","col_count":7,"__link":"_level_1_sprite_right","__class":"Sprite","width_value":32,"row_count":2},{"height_value":32,"row_count":2,"col_count":7,"__link":"_level_1_sprite_left","__class":"Sprite","width_value":32,"texture_name":"player1_level_1_left.png"},{"height_value":64,"col_count":7,"__link":"_level_2_sprite_right","__class":"Sprite","width_value":32,"texture_name":"player1_level_2_right.png"},{"height_value":64,"col_count":7,"__link":"_level_2_sprite_left","__class":"Sprite","width_value":32,"texture_name":"player1_level_2_left.png"},{"height_value":64,"col_count":7,"__link":"_level_3_sprite_right","__class":"Sprite","width_value":32,"texture_name":"player1_level_3_right.png"},{"height_value":64,"col_count":7,"__link":"_level_3_sprite_left","__class":"Sprite","width_value":32,"texture_name":"player1_level_3_left.png"}],"__class":"DisplayLayout","width_value":32,"__target_class":["SuperMarioBros","BattlePlayer"]}}