{"ide_setting_textbutton_extend":{"__childs":[{"data_list":["无","选择文件","选择文件夹"],"width_value":94,"y_value":227.41666666667,"__event":[{"type":"ALittle.UISelectChangedEvent","func":"HandleHandFileSelectSELECT_CHANGE"}],"__extends":"ide_common_dropdown","__link":"_file_select","x_value":93},{"text":"点击弹出选择框","__extends":"ide_common_tab_text_selected","y_value":229.91666666667,"x_value":2.33333333333},{"x_value":39,"__extends":"ide_common_tab_text_selected","y_value":5,"text":"内容"},{"width_value":100,"y_value":3,"__link":"_text","__extends":"ide_common_image_input","__event":[{"type":"ALittle.UIEnterKeyEvent","func":"HandleMTextFOCUSOUT"},{"type":"ALittle.UIFocusOutEvent","func":"HandleMTextFOCUSOUT"}],"x_value":65},{"text":"弹起时图片","__event":[{"type":"ALittle.UILButtonDownEvent","func":"HandleShowUpSelect"}],"y_value":31,"underline":true,"__extends":"ide_common_tab_text_selected","hand_cursor":true,"x_value":3},{"width_value":130,"y_value":28,"__link":"_show_up","__extends":"ide_common_image_input","__event":[{"type":"ALittle.UIEnterKeyEvent","func":"HandleShowUpFOCUSOUT"},{"type":"ALittle.UIFocusOutEvent","func":"HandleShowUpFOCUSOUT"},{"type":"ALittle.UIFocusInEvent","func":"HandleCommonInputFOCUSIN"}],"x_value":65},{"x_value":197,"y_value":29,"__link":"_show_up_grid9","__extends":"ide_common_g9_checkbutton","__event":[{"type":"ALittle.UIChangedEvent","func":"HandleShowUpFOCUSOUT"}],"text":"九宫格"},{"text":"悬停时图片","__event":[{"type":"ALittle.UILButtonDownEvent","func":"HandleShowOverSelect"}],"y_value":57,"underline":true,"__extends":"ide_common_tab_text_selected","hand_cursor":true,"x_value":3},{"width_value":130,"y_value":53,"__link":"_show_over","__extends":"ide_common_image_input","__event":[{"type":"ALittle.UIEnterKeyEvent","func":"HandleShowOverFOCUSOUT"},{"type":"ALittle.UIFocusOutEvent","func":"HandleShowOverFOCUSOUT"},{"type":"ALittle.UIFocusInEvent","func":"HandleCommonInputFOCUSIN"}],"x_value":65},{"x_value":197,"y_value":53,"__link":"_show_over_grid9","__extends":"ide_common_g9_checkbutton","__event":[{"type":"ALittle.UIChangedEvent","func":"HandleShowOverFOCUSOUT"}],"text":"九宫格"},{"text":"按下时图片","__event":[{"type":"ALittle.UILButtonDownEvent","func":"HandleShowDownSelect"}],"y_value":82,"underline":true,"__extends":"ide_common_tab_text_selected","hand_cursor":true,"x_value":3},{"width_value":130,"y_value":78,"__link":"_show_down","__extends":"ide_common_image_input","__event":[{"type":"ALittle.UIEnterKeyEvent","func":"HandleShowDownFOCUSOUT"},{"type":"ALittle.UIFocusOutEvent","func":"HandleShowDownFOCUSOUT"},{"type":"ALittle.UIFocusInEvent","func":"HandleCommonInputFOCUSIN"}],"x_value":65},{"x_value":197,"y_value":78,"__link":"_show_down_grid9","__extends":"ide_common_g9_checkbutton","__event":[{"type":"ALittle.UIChangedEvent","func":"HandleShowDownFOCUSOUT"}],"text":"九宫格"},{"text":"禁用时图片","__event":[{"type":"ALittle.UILButtonDownEvent","func":"HandleShowDisabledSelect"}],"y_value":106,"underline":true,"__extends":"ide_common_tab_text_selected","hand_cursor":true,"x_value":3},{"width_value":130,"y_value":103,"__link":"_show_disabled","__extends":"ide_common_image_input","__event":[{"type":"ALittle.UIEnterKeyEvent","func":"HandleShowDisabledFOCUSOUT"},{"type":"ALittle.UIFocusOutEvent","func":"HandleShowDisabledFOCUSOUT"},{"type":"ALittle.UIFocusInEvent","func":"HandleCommonInputFOCUSIN"}],"x_value":65},{"x_value":197,"y_value":103,"__link":"_show_disabled_grid9","__extends":"ide_common_g9_checkbutton","__event":[{"type":"ALittle.UIChangedEvent","func":"HandleShowDisabledFOCUSOUT"}],"text":"九宫格"},{"x_value":3,"__extends":"ide_common_tab_text_selected","y_value":130,"text":"弹起时字体"},{"width_value":75,"y_value":128,"disabled":true,"__extends":"ide_common_image_input","__link":"_show_text","x_value":65},{"y_value":129,"text":"设置","__extends":"ide_common_usual_button","__event":[{"type":"ALittle.UIClickEvent","func":"HandleShowTextFOCUSOUT"}],"x_value":143},{"y_value":129,"text":"清空","__extends":"ide_common_usual_button","__event":[{"type":"ALittle.UIClickEvent","func":"HandleShowTextClear"}],"x_value":198},{"x_value":3,"__extends":"ide_common_tab_text_selected","y_value":157,"text":"悬停时字体"},{"width_value":75,"y_value":153,"disabled":true,"__extends":"ide_common_image_input","__link":"_show_over_text","x_value":65},{"y_value":153,"text":"设置","__extends":"ide_common_usual_button","__event":[{"type":"ALittle.UIClickEvent","func":"HandleShowOverTextFOCUSOUT"}],"x_value":143},{"y_value":153,"text":"清空","__extends":"ide_common_usual_button","__event":[{"type":"ALittle.UIClickEvent","func":"HandleShowOverTextClear"}],"x_value":198},{"x_value":3,"__extends":"ide_common_tab_text_selected","y_value":181,"text":"按下是字体"},{"width_value":75,"y_value":178,"disabled":true,"__extends":"ide_common_image_input","__link":"_show_down_text","x_value":65},{"y_value":178,"text":"设置","__extends":"ide_common_usual_button","__event":[{"type":"ALittle.UIClickEvent","func":"HandleShowDownTextFOCUSOUT"}],"x_value":143},{"y_value":178,"text":"清空","__extends":"ide_common_usual_button","__event":[{"type":"ALittle.UIClickEvent","func":"HandleShowDownTextClear"}],"x_value":198},{"x_value":3,"__extends":"ide_common_tab_text_selected","y_value":208,"text":"禁用时字体"},{"width_value":75,"y_value":203,"disabled":true,"__extends":"ide_common_image_input","__link":"_show_disabled_text","x_value":65},{"y_value":203,"text":"设置","__extends":"ide_common_usual_button","__event":[{"type":"ALittle.UIClickEvent","func":"HandleShowDisabledTextFOCUSOUT"}],"x_value":143},{"y_value":203,"text":"清空","__extends":"ide_common_usual_button","__event":[{"type":"ALittle.UIClickEvent","func":"HandleShowDisabledTextClear"}],"x_value":198},{"y_value":254.625,"__extends":"ide_common_tab_text_selected","x_value":3,"text":"文本 x类型"},{"data_list":["绝对位置","起始对齐","居中对齐","末尾对齐","起始百分比","居中百分比","末尾百分比"],"y_value":251.625,"width_value":100,"__link":"_text_x_type","__extends":"ide_common_dropdown","__event":[{"type":"ALittle.UISelectChangedEvent","func":"HandleTextXTypeSELECT_CHANGE"}],"x_value":69},{"x_value":175,"__extends":"ide_common_tab_text_selected","y_value":254.625,"text":"x值"},{"width_value":50,"y_value":251.125,"__link":"_text_x_value","__extends":"ide_common_image_input","__event":[{"type":"ALittle.UIEnterKeyEvent","func":"HandleTextXValueFOCUSOUT"},{"type":"ALittle.UIFocusOutEvent","func":"HandleTextXValueFOCUSOUT"}],"x_value":200}],"width_type":4,"height_value":277,"__class":"DisplayLayout"}}