{"controller":{"__target_class":["NESEmulator","GController"],"height_value":166,"width_type":4,"__class":"DisplayLayout","__childs":[{"width_value":110,"__extends":"usual_control_dir_button","__event":[{"func":"HandleDragBegin","type":"ALittle.UIButtonDragBeginEvent"},{"func":"HandleDrag","type":"ALittle.UIButtonDragEvent"},{"func":"HandleDragEnd","type":"ALittle.UIButtonDragEndEvent"},{"func":"HandleLButtonDown","type":"ALittle.UILButtonDownEvent"},{"func":"HandleLButtonUp","type":"ALittle.UILButtonUpEvent"}],"y_type":3,"__module":"AUIPlugin","height_value":110,"x_value":46},{"width_value":71,"__extends":"usual_control_dir_button","__event":[{"func":"HandleSelectDown","type":"ALittle.UILButtonDownEvent"},{"func":"HandleSelectUp","type":"ALittle.UILButtonUpEvent"}],"__module":"AUIPlugin","y_type":4,"height_value":33,"text":"SELECT","x_type":3,"y_value":10,"x_value":-36.5},{"width_value":71,"__extends":"usual_control_dir_button","__event":[{"func":"HandleStartDown","type":"ALittle.UILButtonDownEvent"},{"func":"HandleStartUp","type":"ALittle.UILButtonUpEvent"}],"__module":"AUIPlugin","y_type":4,"height_value":33,"text":"START","x_type":3,"y_value":10,"x_value":49.5},{"width_value":54,"__extends":"usual_control_dir_button","__event":[{"func":"HandleBDown","type":"ALittle.UILButtonDownEvent"},{"func":"HandleBUp","type":"ALittle.UILButtonUpEvent"}],"__module":"AUIPlugin","y_type":3,"height_value":58,"text":"B","x_type":4,"y_value":1,"x_value":89.5},{"width_value":54,"__extends":"usual_control_dir_button","__module":"AUIPlugin","__event":[{"func":"HandleADown","type":"ALittle.UILButtonDownEvent"},{"func":"HandleAUp","type":"ALittle.UILButtonUpEvent"}],"height_value":58,"y_type":3,"x_type":4,"text":"A","x_value":9.5}]}}