{"main_scene":{"__class":"DisplayLayout","height_type":4,"__childs":[{"__class":"Grid3","height_type":4,"width_type":4,"show_up":{"__class":"DisplayLayout","height_type":4,"__childs":[{"__class":"Quad","height_type":4,"width_type":4,"red":0.2,"green":0.2,"blue":0.2},{"__class":"Linear","height_value":22,"y_type":3,"width_type":4,"__childs":[{"text":"设置","__event":[{"type":"ALittle.UIClickEvent","func":"HandleShowSettingDialog"}],"__module":"AUIPlugin","__extends":"usual_button"},{"text":"版本","__event":[{"type":"ALittle.UIClickEvent","func":"HandleShowVersionDialog"}],"__module":"AUIPlugin","__extends":"usual_button"}],"gap":5,"x_value":5}],"width_type":4},"show_center":{"__class":"DisplayLayout","height_type":4,"__childs":[{"__class":"Quad","height_type":4,"width_type":4,"red":0.14509803921569,"green":0.14509803921569,"blue":0.14901960784314},{"height_type":4,"__module":"AUIPlugin","width_type":4,"__link":"_main_tab","__childs":[{"__class":"DisplayLayout","height_type":4,"__childs":[{"__class":"Grid3","y_type":3,"width_type":4,"__link":"_main_grid3_lr","x_type":3,"gap":1,"up_size":350,"height_type":4,"show_down":{"__class":"DisplayLayout","height_type":4,"__childs":[{"__class":"Grid3","height_type":4,"show_center":{"__class":"DisplayLayout","height_type":4,"__childs":[{"__class":"Quad","height_value":20,"red":0.2,"width_type":4,"green":0.2,"blue":0.2},{"__class":"Grid3","width_type":4,"down_size":52,"x_type":3,"gap":2,"y_value":21,"height_value":23,"type":1,"show_down":{"__module":"AUIPlugin","__event":[{"type":"ALittle.UIClickEvent","func":"HandleShowSearchClick"}],"text":"搜索","__extends":"usual_button"},"show_center":{"__link":"_show_search_key","__event":[{"type":"ALittle.UIEnterKeyEvent","func":"HandleShowSearchClick"},{"type":"ALittle.UIChangedEvent","func":"HandleShowSearchClick"}],"__module":"AUIPlugin","__extends":"image_input"},"width_value":10},{"__class":"Text","x_value":3,"font_path":"Miui-Regular.ttf","y_value":1,"text":"详细内容","font_size":12},{"__class":"Quad","__event":[{"type":"ALittle.UIButtonDragEvent","func":"HandleDragRightQuadUD"},{"type":"ALittle.UIButtonDragEndEvent","func":"HandleDragEndRightQuadUD"},{"type":"ALittle.UIMoveInEvent","func":"HandleSetVDragCursor"},{"type":"ALittle.UIMoveOutEvent","func":"HandleSetNormalCursor"}],"width_type":4,"alpha":0,"height_value":4},{"__class":"DisplayLayout","y_type":4,"width_type":4,"__link":"_json_container","x_type":3,"width_value":10,"y_value":5,"height_value":52,"height_type":4}],"width_type":4,"y_value":305},"description":"右边","__link":"_right_grad3_ud","up_size":200,"width_type":4,"show_up":{"__class":"DisplayLayout","height_type":4,"__childs":[{"__class":"Quad","height_value":20,"red":0.2,"width_type":4,"green":0.2,"blue":0.2},{"__class":"Grid3","width_type":4,"down_size":156,"x_type":3,"gap":2,"y_value":21,"height_value":23,"type":1,"show_down":{"__class":"DisplayLayout","height_type":4,"__childs":[{"__module":"AUIPlugin","__event":[{"type":"ALittle.UIClickEvent","func":"HandleLogSearchClick"}],"text":"搜索","__extends":"usual_button"},{"__event":[{"type":"ALittle.UIClickEvent","func":"HandleLogClearClick"}],"__module":"AUIPlugin","x_value":53,"text":"清空","__extends":"usual_button"},{"__event":[{"type":"ALittle.UIClickEvent","func":"HandleLogFliterClick"}],"__module":"AUIPlugin","x_value":106,"text":"过滤","__extends":"usual_button"}],"width_type":4},"show_center":{"__link":"_log_search_key","__event":[{"type":"ALittle.UIChangedEvent","func":"HandleLogSearchClick"}],"__module":"AUIPlugin","__extends":"image_input"},"width_value":10},{"y_type":4,"open_extends_drag":true,"__link":"_log_scroll_screen","x_type":3,"width_value":10,"__extends":"scroll_screen","y_value":5,"height_value":52,"__module":"AUIPlugin","height_type":4,"width_type":4},{"__class":"Text","x_value":3,"font_path":"Miui-Regular.ttf","y_value":1,"text":"日志列表","font_size":12}],"width_type":4,"y_value":4}}],"width_type":4,"description":"右边"},"type":1,"show_center":{"__class":"DisplayLayout","height_type":4,"__childs":[{"__class":"DisplayLayout","height_type":4,"__childs":[{"__class":"Quad","height_value":20,"red":0.2,"width_type":4,"green":0.2,"blue":0.2},{"__class":"Text","x_value":3,"font_path":"Miui-Regular.ttf","y_value":1,"text":"协议内容","font_size":12},{"y_type":4,"open_extends_drag":true,"__link":"_detail_scroll_screen","x_type":3,"width_value":10,"__extends":"scroll_screen","y_value":5,"height_value":50,"__module":"AUIPlugin","height_type":4,"width_type":4},{"__link":"_send_button","x_type":4,"width_value":58,"__extends":"usual_button","y_value":20,"__event":[{"type":"ALittle.UIClickEvent","func":"HandleSendClick"}],"__module":"AUIPlugin","text":"发送","x_value":6}],"width_type":4,"description":"中间底板"},{"__class":"Quad","__event":[{"type":"ALittle.UIButtonDragEvent","func":"HandleDragRightQuadLR"},{"type":"ALittle.UIButtonDragEndEvent","func":"HandleDragEndRightQuadLR"},{"type":"ALittle.UIMoveInEvent","func":"HandleSetHDragCursor"},{"type":"ALittle.UIMoveOutEvent","func":"HandleSetNormalCursor"}],"height_type":4,"x_type":4,"width_value":4,"alpha":0}],"width_type":4,"description":"中间"},"show_up":{"__class":"DisplayLayout","height_type":4,"__childs":[{"__class":"Grid3","height_type":4,"description":"左边","down_size":250,"show_down":{"__class":"DisplayLayout","height_type":4,"__childs":[{"__class":"Quad","height_value":20,"red":0.2,"width_type":4,"green":0.2,"blue":0.2},{"__class":"Text","x_value":176,"font_path":"Miui-Regular.ttf","y_value":25.25,"text":":","font_size":12},{"y_value":22,"__event":[{"type":"ALittle.UISelectChangedEvent","func":"HandleIpSelectChanged"}],"__module":"AUIPlugin","__link":"_ip_dropdown","x_value":31,"width_value":136,"__extends":"dropdown"},{"y_value":21.75,"x_value":189,"__module":"AUIPlugin","__link":"_login_port_input","width_value":62,"__extends":"image_input"},{"y_value":22,"__event":[{"type":"ALittle.UIClickEvent","func":"HandleLogoutClick"}],"__module":"AUIPlugin","x_value":257,"__link":"_logout_button","width_value":73,"text":"断开","__extends":"usual_button"},{"y_value":22,"__event":[{"type":"ALittle.UIClickEvent","func":"HandleLoginClick"}],"__module":"AUIPlugin","x_value":257,"__link":"_login_button","width_value":73,"text":"登录","__extends":"usual_button"},{"__class":"Text","x_value":3,"font_path":"Miui-Regular.ttf","y_value":1,"text":"登录","font_size":12},{"__class":"Text","x_value":8,"font_path":"Miui-Regular.ttf","y_value":25.25,"text":"IP","font_size":12},{"y_type":4,"width_type":4,"__link":"_login_scroll_screen","x_type":3,"width_value":10,"__extends":"scroll_screen","y_value":5,"height_value":52,"__module":"AUIPlugin","height_type":4,"open_extends_drag":true},{"y_value":23.75,"x_value":32,"__module":"AUIPlugin","__link":"_login_ip_input","width_value":114,"__extends":"text_input"}],"width_type":4},"show_center":{"__class":"DisplayLayout","height_type":4,"__childs":[{"__class":"Quad","height_value":20,"red":0.2,"width_type":4,"green":0.2,"blue":0.2},{"__class":"Grid3","width_type":4,"down_size":52,"x_type":3,"gap":2,"y_value":21,"height_value":23,"type":1,"show_down":{"__module":"AUIPlugin","__event":[{"type":"ALittle.UIClickEvent","func":"HandleProtoSearchClick"}],"text":"搜索","__extends":"usual_button"},"show_center":{"__link":"_proto_search_key","__event":[{"type":"ALittle.UIEnterKeyEvent","func":"HandleProtoSearchClick"},{"type":"ALittle.UIChangedEvent","func":"HandleProtoSearchClick"}],"__module":"AUIPlugin","__extends":"image_input"},"width_value":2},{"y_type":4,"width_type":4,"__link":"_protobuf_scroll_screen","x_type":3,"width_value":2,"__extends":"scroll_screen","y_value":5,"height_value":52,"__module":"AUIPlugin","height_type":4,"open_extends_drag":true},{"__class":"Text","x_value":3,"font_path":"Miui-Regular.ttf","y_value":1,"text":"协议","font_size":12}],"width_type":4},"width_type":4}],"width_type":4,"description":"左边"},"down_size":400}],"width_type":4,"__link":"_gclient","__target_class":["Emulator","GClient"],"description":"客户端模式"},{"__class":"Grid3","height_type":4,"description":"机器人模式","width_type":4}],"__extends":"tab"}],"width_type":4},"up_size":35}],"width_type":4}}